aplicacion_venta_respivalle-0.1.0.dist-info/licenses/LICENCE
aplicacion_ventas/__init__.py
aplicacion_ventas/descuentos.py
aplicacion_ventas/exception.py
aplicacion_ventas/gestor_ventas.py
aplicacion_ventas/impuestos.py
aplicacion_ventas/precios.py
tests/__init__.py
tests/test_aplicacion_ventas.py
aplicacion_venta_respivalle-0.1.0.dist-info/METADATA
aplicacion_venta_respivalle-0.1.0.dist-info/WHEEL
aplicacion_venta_respivalle-0.1.0.dist-info/top_level.txt
aplicacion_venta_respivalle-0.1.0.dist-info/RECORD
